ldmat/__init__.py
ldmat/__main__.py
ldmat-0.1.7.dist-info/LICENSE
ldmat-0.1.7.dist-info/METADATA
ldmat-0.1.7.dist-info/WHEEL
ldmat-0.1.7.dist-info/entry_points.txt
ldmat-0.1.7.dist-info/top_level.txt
ldmat-0.1.7.dist-info/RECORD
