Metadata-Version: 2.1
Name: ldmat
Version: 0.1.7
Summary: Efficient Storage and Querying of Linkage Disequilibrium Matrices
Home-page: https://github.com/G2Lab/ldmat
Author: Rockwell Weiner
Author-email: rockwellw@gmail.com
License: MIT
Classifier: Programming Language :: Python :: 3
Classifier: License :: OSI Approved :: MIT License
Classifier: Operating System :: OS Independent
License-File: LICENSE
Requires-Dist: click (>=8.1.3)
Requires-Dist: h5py (>=3.7.0)
Requires-Dist: matplotlib (>=3.4.3)
Requires-Dist: numpy (>=1.21.3)
Requires-Dist: pandas (>=1.3.4)
Requires-Dist: scipy (>=1.8.1)
Requires-Dist: seaborn (>=0.11.2)
